cahmml/__init__.py
cahmml/hmm.py
cahmml/test/test_hmm.py
cahmml/util.py
cahmml-1.0.2.dist-info/LICENSE.txt
cahmml-1.0.2.dist-info/WHEEL
cahmml-1.0.2.dist-info/METADATA
cahmml-1.0.2.dist-info/RECORD
