Metadata-Version: 2.1
Name: cahmml
Version: 1.0.2
Summary: Custom Lambda HMM Library
Author: Ryan Eveloff, Denghui Chen
Requires-Python: >=3.9,<4.0
Classifier: Programming Language :: Python :: 3
Classifier: Programming Language :: Python :: 3.10
Classifier: Programming Language :: Python :: 3.9
Requires-Dist: numpy (>=1.23.5)
Requires-Dist: rich (>=12.6.0)
